[
  {
    "word": "abandonner",
    "article": "",
    "pos": "verb",
    "full_entry": "abandonner"
  },
  {
    "word": "abricot",
    "article": "l'",
    "pos": "noun",
    "full_entry": "l' abricot"
  },
  {
    "word": "abriter",
    "article": "",
    "pos": "verb",
    "full_entry": "abriter"
  },
  {
    "word": "accomplir",
    "article": "",
    "pos": "verb",
    "full_entry": "accomplir"
  },
  {
    "word": "accord",
    "article": "l'",
    "pos": "noun",
    "full_entry": "l' accord"
  },
  {
    "word": "achat",
    "article": "l'",
    "pos": "noun",
    "full_entry": "l' achat"
  },
  {
    "word": "actif",
    "article": "",
    "pos": "adj",
    "full_entry": "actif"
  },
  {
    "word": "actualité",
    "article": "l'",
    "pos": "noun",
    "full_entry": "l' actualité"
  },
  {
    "word": "actuellement",
    "article": "",
    "pos": "adv",
    "full_entry": "actuellement"
  },
  {
    "word": "adapter",
    "article": "",
    "pos": "verb",
    "full_entry": "adapter"
  },
  {
    "word": "addition",
    "article": "l'",
    "pos": "noun",
    "full_entry": "l' addition"
  },
  {
    "word": "administratif",
    "article": "",
    "pos": "adj",
    "full_entry": "administratif"
  },
  {
    "word": "admirable",
    "article": "",
    "pos": "adj",
    "full_entry": "admirable"
  },
  {
    "word": "adolescent",
    "article": "l'",
    "pos": "noun",
    "full_entry": "l' adolescent"
  },
  {
    "word": "affiche",
    "article": "l'",
    "pos": "noun",
    "full_entry": "l' affiche"
  },
  {
    "word": "affoler",
    "article": "",
    "pos": "verb",
    "full_entry": "affoler"
  },
  {
    "word": "agir",
    "article": "",
    "pos": "verb",
    "full_entry": "agir"
  },
  {
    "word": "ailleurs",
    "article": "",
    "pos": "adv",
    "full_entry": "ailleurs"
  },
  {
    "word": "ajoute",
    "article": "l'",
    "pos": "noun",
    "full_entry": "l' ajoute"
  },
  {
    "word": "album",
    "article": "l'",
    "pos": "noun",
    "full_entry": "l' album"
  },
  {
    "word": "alcool",
    "article": "l'",
    "pos": "noun",
    "full_entry": "l' alcool"
  },
  {
    "word": "aliment",
    "article": "l'",
    "pos": "noun",
    "full_entry": "l' aliment"
  },
  {
    "word": "alimentation",
    "article": "l'",
    "pos": "noun",
    "full_entry": "l' alimentation"
  },
  {
    "word": "allemand",
    "article": "l'",
    "pos": "noun",
    "full_entry": "l' allemand"
  },
  {
    "word": "allonger",
    "article": "",
    "pos": "verb",
    "full_entry": "allonger"
  },
  {
    "word": "amateur",
    "article": "",
    "pos": "noun",
    "full_entry": "amateur"
  },
  {
    "word": "ambassade",
    "article": "l'",
    "pos": "noun",
    "full_entry": "l' ambassade"
  },
  {
    "word": "ambiance",
    "article": "l'",
    "pos": "noun",
    "full_entry": "l' ambiance"
  },
  {
    "word": "amitié",
    "article": "l'",
    "pos": "noun",
    "full_entry": "l' amitié"
  },
  {
    "word": "américain",
    "article": "",
    "pos": "adj",
    "full_entry": "américain"
  },
  {
    "word": "angle",
    "article": "l'",
    "pos": "noun",
    "full_entry": "l' angle"
  },
  {
    "word": "animal",
    "article": "",
    "pos": "adj",
    "full_entry": "animal"
  },
  {
    "word": "animation",
    "article": "l'",
    "pos": "noun",
    "full_entry": "l' animation"
  },
  {
    "word": "animer",
    "article": "",
    "pos": "verb",
    "full_entry": "animer"
  },
  {
    "word": "appartenir",
    "article": "",
    "pos": "verb",
    "full_entry": "appartenir"
  },
  {
    "word": "applaudir",
    "article": "",
    "pos": "verb",
    "full_entry": "applaudir"
  },
  {
    "word": "apprenti",
    "article": "l'",
    "pos": "noun",
    "full_entry": "l' apprenti"
  },
  {
    "word": "appuyer",
    "article": "",
    "pos": "verb",
    "full_entry": "appuyer"
  },
  {
    "word": "architecte",
    "article": "",
    "pos": "noun",
    "full_entry": "architecte"
  },
  {
    "word": "architecture",
    "article": "l'",
    "pos": "noun",
    "full_entry": "l' architecture"
  },
  {
    "word": "archéologue",
    "article": "",
    "pos": "noun",
    "full_entry": "archéologue"
  },
  {
    "word": "article",
    "article": "l'",
    "pos": "noun",
    "full_entry": "l' article"
  },
  {
    "word": "artifice",
    "article": "l'",
    "pos": "noun",
    "full_entry": "l' artifice"
  },
  {
    "word": "artiste",
    "article": "",
    "pos": "noun",
    "full_entry": "artiste"
  },
  {
    "word": "assistant",
    "article": "l'",
    "pos": "noun",
    "full_entry": "l' assistant"
  },
  {
    "word": "attaquer",
    "article": "",
    "pos": "verb",
    "full_entry": "attaquer"
  },
  {
    "word": "attraper",
    "article": "",
    "pos": "verb",
    "full_entry": "attraper"
  },
  {
    "word": "auberge",
    "article": "l'",
    "pos": "noun",
    "full_entry": "l' auberge"
  },
  {
    "word": "australien",
    "article": "",
    "pos": "adj",
    "full_entry": "australien"
  },
  {
    "word": "autant",
    "article": "",
    "pos": "adv",
    "full_entry": "autant"
  },
  {
    "word": "auteur",
    "article": "l'",
    "pos": "noun",
    "full_entry": "l' auteur"
  },
  {
    "word": "autoriser",
    "article": "",
    "pos": "verb",
    "full_entry": "autoriser"
  },
  {
    "word": "autoroute",
    "article": "l'",
    "pos": "noun",
    "full_entry": "l' autoroute"
  },
  {
    "word": "avant",
    "article": "l'",
    "pos": "noun",
    "full_entry": "l' avant"
  },
  {
    "word": "avant",
    "article": "",
    "pos": "adv",
    "full_entry": "avant"
  },
  {
    "word": "avantage",
    "article": "l'",
    "pos": "noun",
    "full_entry": "l' avantage"
  },
  {
    "word": "avouer",
    "article": "",
    "pos": "verb",
    "full_entry": "avouer"
  },
  {
    "word": "bac",
    "article": "le",
    "pos": "noun",
    "full_entry": "le bac"
  },
  {
    "word": "baguette",
    "article": "la",
    "pos": "noun",
    "full_entry": "la baguette"
  },
  {
    "word": "balle",
    "article": "la",
    "pos": "noun",
    "full_entry": "la balle"
  },
  {
    "word": "ballon",
    "article": "le",
    "pos": "noun",
    "full_entry": "le ballon"
  },
  {
    "word": "banane",
    "article": "la",
    "pos": "noun",
    "full_entry": "la banane"
  },
  {
    "word": "bancaire",
    "article": "",
    "pos": "adj",
    "full_entry": "bancaire"
  },
  {
    "word": "base",
    "article": "la",
    "pos": "noun",
    "full_entry": "la base"
  },
  {
    "word": "basket",
    "article": "",
    "pos": "noun",
    "full_entry": "basket"
  },
  {
    "word": "bavarder",
    "article": "",
    "pos": "verb",
    "full_entry": "bavarder"
  },
  {
    "word": "beau-frère",
    "article": "le",
    "pos": "noun",
    "full_entry": "le beau-frère"
  },
  {
    "word": "beauté",
    "article": "la",
    "pos": "noun",
    "full_entry": "la beauté"
  },
  {
    "word": "beaux-arts",
    "article": "le",
    "pos": "noun",
    "full_entry": "le beaux-arts"
  },
  {
    "word": "belle-mère",
    "article": "",
    "pos": "noun",
    "full_entry": "belle-mère"
  },
  {
    "word": "ben",
    "article": "le",
    "pos": "noun",
    "full_entry": "le ben"
  },
  {
    "word": "bibliothèque",
    "article": "la",
    "pos": "noun",
    "full_entry": "la bibliothèque"
  },
  {
    "word": "bisou",
    "article": "le",
    "pos": "noun",
    "full_entry": "le bisou"
  },
  {
    "word": "bistrot",
    "article": "le",
    "pos": "noun",
    "full_entry": "le bistrot"
  },
  {
    "word": "blessure",
    "article": "la",
    "pos": "noun",
    "full_entry": "la blessure"
  },
  {
    "word": "blé",
    "article": "le",
    "pos": "noun",
    "full_entry": "le blé"
  },
  {
    "word": "bon",
    "article": "le",
    "pos": "noun",
    "full_entry": "le bon"
  },
  {
    "word": "botte",
    "article": "la",
    "pos": "noun",
    "full_entry": "la botte"
  },
  {
    "word": "bouche",
    "article": "la",
    "pos": "noun",
    "full_entry": "la bouche"
  },
  {
    "word": "boulanger",
    "article": "le",
    "pos": "noun",
    "full_entry": "le boulanger"
  },
  {
    "word": "boulangerie",
    "article": "la",
    "pos": "noun",
    "full_entry": "la boulangerie"
  },
  {
    "word": "bouquet",
    "article": "le",
    "pos": "noun",
    "full_entry": "le bouquet"
  },
  {
    "word": "bourgeois",
    "article": "",
    "pos": "adj",
    "full_entry": "bourgeois"
  },
  {
    "word": "bowling",
    "article": "le",
    "pos": "noun",
    "full_entry": "le bowling"
  },
  {
    "word": "brave",
    "article": "",
    "pos": "adj",
    "full_entry": "brave"
  },
  {
    "word": "brésilien",
    "article": "",
    "pos": "adj",
    "full_entry": "brésilien"
  },
  {
    "word": "brûler",
    "article": "",
    "pos": "verb",
    "full_entry": "brûler"
  },
  {
    "word": "bulletin",
    "article": "le",
    "pos": "noun",
    "full_entry": "le bulletin"
  },
  {
    "word": "bêtise",
    "article": "la",
    "pos": "noun",
    "full_entry": "la bêtise"
  },
  {
    "word": "cahier",
    "article": "le",
    "pos": "noun",
    "full_entry": "le cahier"
  },
  {
    "word": "caissier",
    "article": "le",
    "pos": "noun",
    "full_entry": "le caissier"
  },
  {
    "word": "camarade",
    "article": "",
    "pos": "noun",
    "full_entry": "camarade"
  },
  {
    "word": "camion",
    "article": "le",
    "pos": "noun",
    "full_entry": "le camion"
  },
  {
    "word": "canadien",
    "article": "",
    "pos": "adj",
    "full_entry": "canadien"
  },
  {
    "word": "candidat",
    "article": "le",
    "pos": "noun",
    "full_entry": "le candidat"
  },
  {
    "word": "canne",
    "article": "la",
    "pos": "noun",
    "full_entry": "la canne"
  },
  {
    "word": "capable",
    "article": "",
    "pos": "adj",
    "full_entry": "capable"
  },
  {
    "word": "car",
    "article": "le",
    "pos": "noun",
    "full_entry": "le car"
  },
  {
    "word": "carnet",
    "article": "le",
    "pos": "noun",
    "full_entry": "le carnet"
  },
  {
    "word": "carrière",
    "article": "",
    "pos": "noun",
    "full_entry": "carrière"
  },
  {
    "word": "casque",
    "article": "le",
    "pos": "noun",
    "full_entry": "le casque"
  },
  {
    "word": "casser",
    "article": "",
    "pos": "verb",
    "full_entry": "casser"
  },
  {
    "word": "cave",
    "article": "la",
    "pos": "noun",
    "full_entry": "la cave"
  },
  {
    "word": "centre-ville",
    "article": "le",
    "pos": "noun",
    "full_entry": "le centre-ville"
  },
  {
    "word": "cependant",
    "article": "",
    "pos": "adv",
    "full_entry": "cependant"
  },
  {
    "word": "chaise",
    "article": "la",
    "pos": "noun",
    "full_entry": "la chaise"
  },
  {
    "word": "chaleureux",
    "article": "",
    "pos": "adj",
    "full_entry": "chaleureux"
  },
  {
    "word": "champ",
    "article": "le",
    "pos": "noun",
    "full_entry": "le champ"
  },
  {
    "word": "champion",
    "article": "le",
    "pos": "noun",
    "full_entry": "le champion"
  },
  {
    "word": "chant",
    "article": "le",
    "pos": "noun",
    "full_entry": "le chant"
  },
  {
    "word": "chapeau",
    "article": "le",
    "pos": "noun",
    "full_entry": "le chapeau"
  },
  {
    "word": "charcuterie",
    "article": "la",
    "pos": "noun",
    "full_entry": "la charcuterie"
  },
  {
    "word": "charité",
    "article": "la",
    "pos": "noun",
    "full_entry": "la charité"
  },
  {
    "word": "charme",
    "article": "le",
    "pos": "noun",
    "full_entry": "le charme"
  },
  {
    "word": "chaîne",
    "article": "la",
    "pos": "noun",
    "full_entry": "la chaîne"
  },
  {
    "word": "chic",
    "article": "",
    "pos": "adj",
    "full_entry": "chic"
  },
  {
    "word": "chiffre",
    "article": "le",
    "pos": "noun",
    "full_entry": "le chiffre"
  },
  {
    "word": "châtain",
    "article": "",
    "pos": "adj",
    "full_entry": "châtain"
  },
  {
    "word": "chèvre",
    "article": "la",
    "pos": "noun",
    "full_entry": "la chèvre"
  },
  {
    "word": "chéri",
    "article": "",
    "pos": "noun",
    "full_entry": "chéri"
  },
  {
    "word": "chômeur",
    "article": "le",
    "pos": "noun",
    "full_entry": "le chômeur"
  },
  {
    "word": "cidre",
    "article": "le",
    "pos": "noun",
    "full_entry": "le cidre"
  },
  {
    "word": "cinquante",
    "article": "",
    "pos": "adj",
    "full_entry": "cinquante"
  },
  {
    "word": "cinquante",
    "article": "le",
    "pos": "noun",
    "full_entry": "le cinquante"
  },
  {
    "word": "ciné",
    "article": "le",
    "pos": "noun",
    "full_entry": "le ciné"
  },
  {
    "word": "cire",
    "article": "la",
    "pos": "noun",
    "full_entry": "la cire"
  },
  {
    "word": "citer",
    "article": "",
    "pos": "verb",
    "full_entry": "citer"
  },
  {
    "word": "classique",
    "article": "",
    "pos": "adj",
    "full_entry": "classique"
  },
  {
    "word": "code",
    "article": "le",
    "pos": "noun",
    "full_entry": "le code"
  },
  {
    "word": "coiffer",
    "article": "",
    "pos": "verb",
    "full_entry": "coiffer"
  },
  {
    "word": "collectionner",
    "article": "",
    "pos": "verb",
    "full_entry": "collectionner"
  },
  {
    "word": "collectionneur",
    "article": "le",
    "pos": "noun",
    "full_entry": "le collectionneur"
  },
  {
    "word": "coller",
    "article": "",
    "pos": "verb",
    "full_entry": "coller"
  },
  {
    "word": "colline",
    "article": "la",
    "pos": "noun",
    "full_entry": "la colline"
  },
  {
    "word": "colonie",
    "article": "la",
    "pos": "noun",
    "full_entry": "la colonie"
  },
  {
    "word": "colorer",
    "article": "",
    "pos": "verb",
    "full_entry": "colorer"
  },
  {
    "word": "combat",
    "article": "le",
    "pos": "noun",
    "full_entry": "le combat"
  },
  {
    "word": "comique",
    "article": "",
    "pos": "adj",
    "full_entry": "comique"
  },
  {
    "word": "commentaire",
    "article": "le",
    "pos": "noun",
    "full_entry": "le commentaire"
  },
  {
    "word": "commenter",
    "article": "",
    "pos": "verb",
    "full_entry": "commenter"
  },
  {
    "word": "commerçant",
    "article": "le",
    "pos": "noun",
    "full_entry": "le commerçant"
  },
  {
    "word": "commissariat",
    "article": "le",
    "pos": "noun",
    "full_entry": "le commissariat"
  },
  {
    "word": "communauté",
    "article": "la",
    "pos": "noun",
    "full_entry": "la communauté"
  },
  {
    "word": "compléter",
    "article": "",
    "pos": "verb",
    "full_entry": "compléter"
  },
  {
    "word": "comptabilité",
    "article": "la",
    "pos": "noun",
    "full_entry": "la comptabilité"
  },
  {
    "word": "comédie",
    "article": "la",
    "pos": "noun",
    "full_entry": "la comédie"
  },
  {
    "word": "comédien",
    "article": "le",
    "pos": "noun",
    "full_entry": "le comédien"
  },
  {
    "word": "concerner",
    "article": "",
    "pos": "verb",
    "full_entry": "concerner"
  },
  {
    "word": "concombre",
    "article": "le",
    "pos": "noun",
    "full_entry": "le concombre"
  },
  {
    "word": "concours",
    "article": "le",
    "pos": "noun",
    "full_entry": "le concours"
  },
  {
    "word": "condition",
    "article": "la",
    "pos": "noun",
    "full_entry": "la condition"
  },
  {
    "word": "conducteur",
    "article": "le",
    "pos": "noun",
    "full_entry": "le conducteur"
  },
  {
    "word": "confirmer",
    "article": "",
    "pos": "verb",
    "full_entry": "confirmer"
  },
  {
    "word": "confortable",
    "article": "",
    "pos": "adj",
    "full_entry": "confortable"
  },
  {
    "word": "congé",
    "article": "le",
    "pos": "noun",
    "full_entry": "le congé"
  },
  {
    "word": "consacrer",
    "article": "",
    "pos": "verb",
    "full_entry": "consacrer"
  },
  {
    "word": "conseiller",
    "article": "",
    "pos": "verb",
    "full_entry": "conseiller"
  },
  {
    "word": "conserver",
    "article": "",
    "pos": "verb",
    "full_entry": "conserver"
  },
  {
    "word": "console",
    "article": "la",
    "pos": "noun",
    "full_entry": "la console"
  },
  {
    "word": "consommer",
    "article": "",
    "pos": "verb",
    "full_entry": "consommer"
  },
  {
    "word": "constater",
    "article": "",
    "pos": "verb",
    "full_entry": "constater"
  },
  {
    "word": "construction",
    "article": "la",
    "pos": "noun",
    "full_entry": "la construction"
  },
  {
    "word": "contact",
    "article": "le",
    "pos": "noun",
    "full_entry": "le contact"
  },
  {
    "word": "contacter",
    "article": "",
    "pos": "verb",
    "full_entry": "contacter"
  },
  {
    "word": "conte",
    "article": "le",
    "pos": "noun",
    "full_entry": "le conte"
  },
  {
    "word": "contemporain",
    "article": "",
    "pos": "adj",
    "full_entry": "contemporain"
  },
  {
    "word": "contre",
    "article": "le",
    "pos": "noun",
    "full_entry": "le contre"
  },
  {
    "word": "convaincre",
    "article": "",
    "pos": "verb",
    "full_entry": "convaincre"
  },
  {
    "word": "conversation",
    "article": "la",
    "pos": "noun",
    "full_entry": "la conversation"
  },
  {
    "word": "corps",
    "article": "le",
    "pos": "noun",
    "full_entry": "le corps"
  },
  {
    "word": "corriger",
    "article": "",
    "pos": "verb",
    "full_entry": "corriger"
  },
  {
    "word": "coupe",
    "article": "la",
    "pos": "noun",
    "full_entry": "la coupe"
  },
  {
    "word": "couscous",
    "article": "le",
    "pos": "noun",
    "full_entry": "le couscous"
  },
  {
    "word": "coutume",
    "article": "la",
    "pos": "noun",
    "full_entry": "la coutume"
  },
  {
    "word": "crise",
    "article": "la",
    "pos": "noun",
    "full_entry": "la crise"
  },
  {
    "word": "critiquer",
    "article": "",
    "pos": "verb",
    "full_entry": "critiquer"
  },
  {
    "word": "croissant",
    "article": "le",
    "pos": "noun",
    "full_entry": "le croissant"
  },
  {
    "word": "crèche",
    "article": "la",
    "pos": "noun",
    "full_entry": "la crèche"
  },
  {
    "word": "crème",
    "article": "",
    "pos": "noun",
    "full_entry": "crème"
  },
  {
    "word": "créole",
    "article": "",
    "pos": "adj",
    "full_entry": "créole"
  },
  {
    "word": "créole",
    "article": "",
    "pos": "noun",
    "full_entry": "créole"
  },
  {
    "word": "cuire",
    "article": "",
    "pos": "verb",
    "full_entry": "cuire"
  },
  {
    "word": "cuisinier",
    "article": "le",
    "pos": "noun",
    "full_entry": "le cuisinier"
  },
  {
    "word": "culinaire",
    "article": "",
    "pos": "adj",
    "full_entry": "culinaire"
  },
  {
    "word": "cultiver",
    "article": "",
    "pos": "verb",
    "full_entry": "cultiver"
  },
  {
    "word": "cultivé",
    "article": "",
    "pos": "adj",
    "full_entry": "cultivé"
  },
  {
    "word": "célibataire",
    "article": "",
    "pos": "adj",
    "full_entry": "célibataire"
  },
  {
    "word": "célébrer",
    "article": "",
    "pos": "verb",
    "full_entry": "célébrer"
  },
  {
    "word": "céréale",
    "article": "la",
    "pos": "noun",
    "full_entry": "la céréale"
  },
  {
    "word": "cérémonie",
    "article": "la",
    "pos": "noun",
    "full_entry": "la cérémonie"
  },
  {
    "word": "danseur",
    "article": "le",
    "pos": "noun",
    "full_entry": "le danseur"
  },
  {
    "word": "dater",
    "article": "",
    "pos": "verb",
    "full_entry": "dater"
  },
  {
    "word": "degré",
    "article": "le",
    "pos": "noun",
    "full_entry": "le degré"
  },
  {
    "word": "dehors",
    "article": "",
    "pos": "adv",
    "full_entry": "dehors"
  },
  {
    "word": "dentiste",
    "article": "",
    "pos": "noun",
    "full_entry": "dentiste"
  },
  {
    "word": "dernier",
    "article": "le",
    "pos": "noun",
    "full_entry": "le dernier"
  },
  {
    "word": "dessinateur",
    "article": "le",
    "pos": "noun",
    "full_entry": "le dessinateur"
  },
  {
    "word": "diable",
    "article": "le",
    "pos": "noun",
    "full_entry": "le diable"
  },
  {
    "word": "dialogue",
    "article": "le",
    "pos": "noun",
    "full_entry": "le dialogue"
  },
  {
    "word": "difficulté",
    "article": "la",
    "pos": "noun",
    "full_entry": "la difficulté"
  },
  {
    "word": "dinde",
    "article": "la",
    "pos": "noun",
    "full_entry": "la dinde"
  },
  {
    "word": "discours",
    "article": "le",
    "pos": "noun",
    "full_entry": "le discours"
  },
  {
    "word": "discussion",
    "article": "la",
    "pos": "noun",
    "full_entry": "la discussion"
  },
  {
    "word": "divers",
    "article": "",
    "pos": "adj",
    "full_entry": "divers"
  },
  {
    "word": "diversité",
    "article": "la",
    "pos": "noun",
    "full_entry": "la diversité"
  },
  {
    "word": "diviser",
    "article": "",
    "pos": "verb",
    "full_entry": "diviser"
  },
  {
    "word": "doigt",
    "article": "le",
    "pos": "noun",
    "full_entry": "le doigt"
  },
  {
    "word": "domestique",
    "article": "",
    "pos": "adj",
    "full_entry": "domestique"
  },
  {
    "word": "double",
    "article": "",
    "pos": "adj",
    "full_entry": "double"
  },
  {
    "word": "douche",
    "article": "la",
    "pos": "noun",
    "full_entry": "la douche"
  },
  {
    "word": "doute",
    "article": "le",
    "pos": "noun",
    "full_entry": "le doute"
  },
  {
    "word": "décevoir",
    "article": "",
    "pos": "verb",
    "full_entry": "décevoir"
  },
  {
    "word": "décision",
    "article": "la",
    "pos": "noun",
    "full_entry": "la décision"
  },
  {
    "word": "déclarer",
    "article": "",
    "pos": "verb",
    "full_entry": "déclarer"
  },
  {
    "word": "décontracter",
    "article": "",
    "pos": "verb",
    "full_entry": "décontracter"
  },
  {
    "word": "décor",
    "article": "le",
    "pos": "noun",
    "full_entry": "le décor"
  },
  {
    "word": "décrire",
    "article": "",
    "pos": "verb",
    "full_entry": "décrire"
  },
  {
    "word": "définir",
    "article": "",
    "pos": "verb",
    "full_entry": "définir"
  },
  {
    "word": "déguiser",
    "article": "",
    "pos": "verb",
    "full_entry": "déguiser"
  },
  {
    "word": "déguster",
    "article": "",
    "pos": "verb",
    "full_entry": "déguster"
  },
  {
    "word": "déménager",
    "article": "",
    "pos": "verb",
    "full_entry": "déménager"
  },
  {
    "word": "dépendre",
    "article": "",
    "pos": "verb",
    "full_entry": "dépendre"
  },
  {
    "word": "déposer",
    "article": "",
    "pos": "verb",
    "full_entry": "déposer"
  },
  {
    "word": "désespérer",
    "article": "",
    "pos": "verb",
    "full_entry": "désespérer"
  },
  {
    "word": "développement",
    "article": "le",
    "pos": "noun",
    "full_entry": "le développement"
  },
  {
    "word": "développer",
    "article": "",
    "pos": "verb",
    "full_entry": "développer"
  },
  {
    "word": "dévorer",
    "article": "",
    "pos": "verb",
    "full_entry": "dévorer"
  },
  {
    "word": "effondrer",
    "article": "",
    "pos": "verb",
    "full_entry": "effondrer"
  },
  {
    "word": "emploi",
    "article": "l'",
    "pos": "noun",
    "full_entry": "l' emploi"
  },
  {
    "word": "enchanter",
    "article": "",
    "pos": "verb",
    "full_entry": "enchanter"
  },
  {
    "word": "enfermer",
    "article": "",
    "pos": "verb",
    "full_entry": "enfermer"
  },
  {
    "word": "engager",
    "article": "",
    "pos": "verb",
    "full_entry": "engager"
  },
  {
    "word": "enlever",
    "article": "",
    "pos": "verb",
    "full_entry": "enlever"
  },
  {
    "word": "ennuyeux",
    "article": "",
    "pos": "adj",
    "full_entry": "ennuyeux"
  },
  {
    "word": "enquête",
    "article": "l'",
    "pos": "noun",
    "full_entry": "l' enquête"
  },
  {
    "word": "enseignement",
    "article": "l'",
    "pos": "noun",
    "full_entry": "l' enseignement"
  },
  {
    "word": "ensoleiller",
    "article": "",
    "pos": "verb",
    "full_entry": "ensoleiller"
  },
  {
    "word": "entier",
    "article": "",
    "pos": "adj",
    "full_entry": "entier"
  },
  {
    "word": "entraîner",
    "article": "",
    "pos": "verb",
    "full_entry": "entraîner"
  },
  {
    "word": "environ",
    "article": "",
    "pos": "adv",
    "full_entry": "environ"
  },
  {
    "word": "escalier",
    "article": "l'",
    "pos": "noun",
    "full_entry": "l' escalier"
  },
  {
    "word": "escargot",
    "article": "l'",
    "pos": "noun",
    "full_entry": "l' escargot"
  },
  {
    "word": "esclave",
    "article": "",
    "pos": "noun",
    "full_entry": "esclave"
  },
  {
    "word": "essentiel",
    "article": "l'",
    "pos": "noun",
    "full_entry": "l' essentiel"
  },
  {
    "word": "exagérer",
    "article": "",
    "pos": "verb",
    "full_entry": "exagérer"
  },
  {
    "word": "exclamer",
    "article": "",
    "pos": "verb",
    "full_entry": "exclamer"
  },
  {
    "word": "exotique",
    "article": "",
    "pos": "adj",
    "full_entry": "exotique"
  },
  {
    "word": "exposer",
    "article": "",
    "pos": "verb",
    "full_entry": "exposer"
  },
  {
    "word": "exprimer",
    "article": "",
    "pos": "verb",
    "full_entry": "exprimer"
  },
  {
    "word": "fac",
    "article": "la",
    "pos": "noun",
    "full_entry": "la fac"
  },
  {
    "word": "fan",
    "article": "",
    "pos": "noun",
    "full_entry": "fan"
  },
  {
    "word": "fatigant",
    "article": "",
    "pos": "adj",
    "full_entry": "fatigant"
  },
  {
    "word": "fatigué",
    "article": "",
    "pos": "adj",
    "full_entry": "fatigué"
  },
  {
    "word": "faveur",
    "article": "la",
    "pos": "noun",
    "full_entry": "la faveur"
  },
  {
    "word": "fer",
    "article": "le",
    "pos": "noun",
    "full_entry": "le fer"
  },
  {
    "word": "fermeture",
    "article": "la",
    "pos": "noun",
    "full_entry": "la fermeture"
  },
  {
    "word": "feuilleton",
    "article": "le",
    "pos": "noun",
    "full_entry": "le feuilleton"
  },
  {
    "word": "fidèle",
    "article": "",
    "pos": "adj",
    "full_entry": "fidèle"
  },
  {
    "word": "fidélité",
    "article": "la",
    "pos": "noun",
    "full_entry": "la fidélité"
  },
  {
    "word": "fier",
    "article": "",
    "pos": "verb",
    "full_entry": "fier"
  },
  {
    "word": "fixer",
    "article": "",
    "pos": "verb",
    "full_entry": "fixer"
  },
  {
    "word": "foie",
    "article": "le",
    "pos": "noun",
    "full_entry": "le foie"
  },
  {
    "word": "fonctionner",
    "article": "",
    "pos": "verb",
    "full_entry": "fonctionner"
  },
  {
    "word": "fond",
    "article": "le",
    "pos": "noun",
    "full_entry": "le fond"
  },
  {
    "word": "fonder",
    "article": "",
    "pos": "verb",
    "full_entry": "fonder"
  },
  {
    "word": "fontaine",
    "article": "la",
    "pos": "noun",
    "full_entry": "la fontaine"
  },
  {
    "word": "football",
    "article": "le",
    "pos": "noun",
    "full_entry": "le football"
  },
  {
    "word": "force",
    "article": "la",
    "pos": "noun",
    "full_entry": "la force"
  },
  {
    "word": "foyer",
    "article": "le",
    "pos": "noun",
    "full_entry": "le foyer"
  },
  {
    "word": "francophonie",
    "article": "la",
    "pos": "noun",
    "full_entry": "la francophonie"
  },
  {
    "word": "français",
    "article": "le",
    "pos": "noun",
    "full_entry": "le français"
  },
  {
    "word": "froid",
    "article": "le",
    "pos": "noun",
    "full_entry": "le froid"
  },
  {
    "word": "fumé",
    "article": "",
    "pos": "adj",
    "full_entry": "fumé"
  },
  {
    "word": "futur",
    "article": "le",
    "pos": "noun",
    "full_entry": "le futur"
  },
  {
    "word": "féminin",
    "article": "",
    "pos": "adj",
    "full_entry": "féminin"
  },
  {
    "word": "férié",
    "article": "",
    "pos": "adj",
    "full_entry": "férié"
  },
  {
    "word": "galerie",
    "article": "la",
    "pos": "noun",
    "full_entry": "la galerie"
  },
  {
    "word": "gamin",
    "article": "le",
    "pos": "noun",
    "full_entry": "le gamin"
  },
  {
    "word": "garage",
    "article": "le",
    "pos": "noun",
    "full_entry": "le garage"
  },
  {
    "word": "garde",
    "article": "",
    "pos": "noun",
    "full_entry": "garde"
  },
  {
    "word": "gardien",
    "article": "le",
    "pos": "noun",
    "full_entry": "le gardien"
  },
  {
    "word": "gendarmerie",
    "article": "la",
    "pos": "noun",
    "full_entry": "la gendarmerie"
  },
  {
    "word": "genre",
    "article": "le",
    "pos": "noun",
    "full_entry": "le genre"
  },
  {
    "word": "glisser",
    "article": "",
    "pos": "verb",
    "full_entry": "glisser"
  },
  {
    "word": "gouvernement",
    "article": "le",
    "pos": "noun",
    "full_entry": "le gouvernement"
  },
  {
    "word": "gramme",
    "article": "le",
    "pos": "noun",
    "full_entry": "le gramme"
  },
  {
    "word": "grand-chose",
    "article": "",
    "pos": "noun",
    "full_entry": "grand-chose"
  },
  {
    "word": "grenouille",
    "article": "la",
    "pos": "noun",
    "full_entry": "la grenouille"
  },
  {
    "word": "grillé",
    "article": "",
    "pos": "adj",
    "full_entry": "grillé"
  },
  {
    "word": "gris",
    "article": "le",
    "pos": "noun",
    "full_entry": "le gris"
  },
  {
    "word": "guitare",
    "article": "la",
    "pos": "noun",
    "full_entry": "la guitare"
  },
  {
    "word": "général",
    "article": "le",
    "pos": "noun",
    "full_entry": "le général"
  },
  {
    "word": "haut",
    "article": "",
    "pos": "adj",
    "full_entry": "haut"
  },
  {
    "word": "historique",
    "article": "",
    "pos": "adj",
    "full_entry": "historique"
  },
  {
    "word": "horaire",
    "article": "l'",
    "pos": "noun",
    "full_entry": "l' horaire"
  },
  {
    "word": "humour",
    "article": "l'",
    "pos": "noun",
    "full_entry": "l' humour"
  },
  {
    "word": "hygiène",
    "article": "l'",
    "pos": "noun",
    "full_entry": "l' hygiène"
  },
  {
    "word": "hypermarché",
    "article": "l'",
    "pos": "noun",
    "full_entry": "l' hypermarché"
  },
  {
    "word": "héler",
    "article": "",
    "pos": "verb",
    "full_entry": "héler"
  },
  {
    "word": "hélicoptère",
    "article": "l'",
    "pos": "noun",
    "full_entry": "l' hélicoptère"
  },
  {
    "word": "héritage",
    "article": "l'",
    "pos": "noun",
    "full_entry": "l' héritage"
  },
  {
    "word": "hésiter",
    "article": "",
    "pos": "verb",
    "full_entry": "hésiter"
  },
  {
    "word": "ignorer",
    "article": "",
    "pos": "verb",
    "full_entry": "ignorer"
  },
  {
    "word": "illuminer",
    "article": "",
    "pos": "verb",
    "full_entry": "illuminer"
  },
  {
    "word": "illustration",
    "article": "l'",
    "pos": "noun",
    "full_entry": "l' illustration"
  },
  {
    "word": "illustrer",
    "article": "",
    "pos": "verb",
    "full_entry": "illustrer"
  },
  {
    "word": "immense",
    "article": "",
    "pos": "adj",
    "full_entry": "immense"
  },
  {
    "word": "impression",
    "article": "l'",
    "pos": "noun",
    "full_entry": "l' impression"
  },
  {
    "word": "inconnu",
    "article": "",
    "pos": "adj",
    "full_entry": "inconnu"
  },
  {
    "word": "indice",
    "article": "l'",
    "pos": "noun",
    "full_entry": "l' indice"
  },
  {
    "word": "indien",
    "article": "",
    "pos": "adj",
    "full_entry": "indien"
  },
  {
    "word": "industriel",
    "article": "",
    "pos": "adj",
    "full_entry": "industriel"
  },
  {
    "word": "infirmier",
    "article": "l'",
    "pos": "noun",
    "full_entry": "l' infirmier"
  },
  {
    "word": "informatique",
    "article": "",
    "pos": "adj",
    "full_entry": "informatique"
  },
  {
    "word": "ingénieur",
    "article": "l'",
    "pos": "noun",
    "full_entry": "l' ingénieur"
  },
  {
    "word": "innocent",
    "article": "",
    "pos": "adj",
    "full_entry": "innocent"
  },
  {
    "word": "inoubliable",
    "article": "",
    "pos": "adj",
    "full_entry": "inoubliable"
  },
  {
    "word": "inquiet",
    "article": "",
    "pos": "adj",
    "full_entry": "inquiet"
  },
  {
    "word": "inscrire",
    "article": "",
    "pos": "verb",
    "full_entry": "inscrire"
  },
  {
    "word": "insister",
    "article": "",
    "pos": "verb",
    "full_entry": "insister"
  },
  {
    "word": "inspecteur",
    "article": "l'",
    "pos": "noun",
    "full_entry": "l' inspecteur"
  },
  {
    "word": "inspirer",
    "article": "",
    "pos": "verb",
    "full_entry": "inspirer"
  },
  {
    "word": "installation",
    "article": "l'",
    "pos": "noun",
    "full_entry": "l' installation"
  },
  {
    "word": "instant",
    "article": "l'",
    "pos": "noun",
    "full_entry": "l' instant"
  },
  {
    "word": "institut",
    "article": "l'",
    "pos": "noun",
    "full_entry": "l' institut"
  },
  {
    "word": "institution",
    "article": "l'",
    "pos": "noun",
    "full_entry": "l' institution"
  },
  {
    "word": "insupportable",
    "article": "",
    "pos": "adj",
    "full_entry": "insupportable"
  },
  {
    "word": "intense",
    "article": "",
    "pos": "adj",
    "full_entry": "intense"
  },
  {
    "word": "invention",
    "article": "l'",
    "pos": "noun",
    "full_entry": "l' invention"
  },
  {
    "word": "invité",
    "article": "",
    "pos": "adj",
    "full_entry": "invité"
  },
  {
    "word": "itinéraire",
    "article": "l'",
    "pos": "noun",
    "full_entry": "l' itinéraire"
  },
  {
    "word": "jaloux",
    "article": "",
    "pos": "adj",
    "full_entry": "jaloux"
  },
  {
    "word": "japonais",
    "article": "",
    "pos": "adj",
    "full_entry": "japonais"
  },
  {
    "word": "jazz",
    "article": "le",
    "pos": "noun",
    "full_entry": "le jazz"
  },
  {
    "word": "jouet",
    "article": "le",
    "pos": "noun",
    "full_entry": "le jouet"
  },
  {
    "word": "joueur",
    "article": "le",
    "pos": "noun",
    "full_entry": "le joueur"
  },
  {
    "word": "juge",
    "article": "le",
    "pos": "noun",
    "full_entry": "le juge"
  },
  {
    "word": "jumeau",
    "article": "le",
    "pos": "noun",
    "full_entry": "le jumeau"
  },
  {
    "word": "justice",
    "article": "",
    "pos": "noun",
    "full_entry": "justice"
  },
  {
    "word": "laboratoire",
    "article": "le",
    "pos": "noun",
    "full_entry": "le laboratoire"
  },
  {
    "word": "laitier",
    "article": "",
    "pos": "adj",
    "full_entry": "laitier"
  },
  {
    "word": "lancer",
    "article": "",
    "pos": "verb",
    "full_entry": "lancer"
  },
  {
    "word": "lapin",
    "article": "le",
    "pos": "noun",
    "full_entry": "le lapin"
  },
  {
    "word": "larme",
    "article": "la",
    "pos": "noun",
    "full_entry": "la larme"
  },
  {
    "word": "latin",
    "article": "",
    "pos": "adj",
    "full_entry": "latin"
  },
  {
    "word": "leçon",
    "article": "la",
    "pos": "noun",
    "full_entry": "la leçon"
  },
  {
    "word": "libération",
    "article": "la",
    "pos": "noun",
    "full_entry": "la libération"
  },
  {
    "word": "libérer",
    "article": "",
    "pos": "verb",
    "full_entry": "libérer"
  },
  {
    "word": "linguistique",
    "article": "",
    "pos": "adj",
    "full_entry": "linguistique"
  },
  {
    "word": "liste",
    "article": "la",
    "pos": "noun",
    "full_entry": "la liste"
  },
  {
    "word": "logement",
    "article": "le",
    "pos": "noun",
    "full_entry": "le logement"
  },
  {
    "word": "loi",
    "article": "la",
    "pos": "noun",
    "full_entry": "la loi"
  },
  {
    "word": "lointain",
    "article": "",
    "pos": "adj",
    "full_entry": "lointain"
  },
  {
    "word": "louer",
    "article": "",
    "pos": "verb",
    "full_entry": "louer"
  },
  {
    "word": "loup",
    "article": "le",
    "pos": "noun",
    "full_entry": "le loup"
  },
  {
    "word": "lourd",
    "article": "",
    "pos": "adj",
    "full_entry": "lourd"
  },
  {
    "word": "luire",
    "article": "",
    "pos": "verb",
    "full_entry": "luire"
  },
  {
    "word": "lune",
    "article": "la",
    "pos": "noun",
    "full_entry": "la lune"
  },
  {
    "word": "léger",
    "article": "",
    "pos": "adj",
    "full_entry": "léger"
  },
  {
    "word": "maire",
    "article": "le",
    "pos": "noun",
    "full_entry": "le maire"
  },
  {
    "word": "malade",
    "article": "",
    "pos": "noun",
    "full_entry": "malade"
  },
  {
    "word": "malheureusement",
    "article": "",
    "pos": "adv",
    "full_entry": "malheureusement"
  },
  {
    "word": "malheureux",
    "article": "",
    "pos": "adj",
    "full_entry": "malheureux"
  },
  {
    "word": "maquette",
    "article": "la",
    "pos": "noun",
    "full_entry": "la maquette"
  },
  {
    "word": "margot",
    "article": "le",
    "pos": "noun",
    "full_entry": "le margot"
  },
  {
    "word": "marocain",
    "article": "",
    "pos": "adj",
    "full_entry": "marocain"
  },
  {
    "word": "marque",
    "article": "la",
    "pos": "noun",
    "full_entry": "la marque"
  },
  {
    "word": "marrant",
    "article": "",
    "pos": "adj",
    "full_entry": "marrant"
  },
  {
    "word": "marre",
    "article": "",
    "pos": "adv",
    "full_entry": "marre"
  },
  {
    "word": "marron",
    "article": "",
    "pos": "adj",
    "full_entry": "marron"
  },
  {
    "word": "mars",
    "article": "",
    "pos": "noun",
    "full_entry": "mars"
  },
  {
    "word": "masque",
    "article": "le",
    "pos": "noun",
    "full_entry": "le masque"
  },
  {
    "word": "maternel",
    "article": "",
    "pos": "adj",
    "full_entry": "maternel"
  },
  {
    "word": "mathématique",
    "article": "la",
    "pos": "noun",
    "full_entry": "la mathématique"
  },
  {
    "word": "mener",
    "article": "",
    "pos": "verb",
    "full_entry": "mener"
  },
  {
    "word": "menthe",
    "article": "la",
    "pos": "noun",
    "full_entry": "la menthe"
  },
  {
    "word": "mentir",
    "article": "",
    "pos": "verb",
    "full_entry": "mentir"
  },
  {
    "word": "merveille",
    "article": "la",
    "pos": "noun",
    "full_entry": "la merveille"
  },
  {
    "word": "mesurer",
    "article": "",
    "pos": "verb",
    "full_entry": "mesurer"
  },
  {
    "word": "mi",
    "article": "le",
    "pos": "noun",
    "full_entry": "le mi"
  },
  {
    "word": "micro",
    "article": "",
    "pos": "noun",
    "full_entry": "micro"
  },
  {
    "word": "mignon",
    "article": "",
    "pos": "adj",
    "full_entry": "mignon"
  },
  {
    "word": "minéral",
    "article": "",
    "pos": "adj",
    "full_entry": "minéral"
  },
  {
    "word": "mistral",
    "article": "le",
    "pos": "noun",
    "full_entry": "le mistral"
  },
  {
    "word": "mixte",
    "article": "",
    "pos": "adj",
    "full_entry": "mixte"
  },
  {
    "word": "moitié",
    "article": "la",
    "pos": "noun",
    "full_entry": "la moitié"
  },
  {
    "word": "monnaie",
    "article": "la",
    "pos": "noun",
    "full_entry": "la monnaie"
  },
  {
    "word": "montant",
    "article": "le",
    "pos": "noun",
    "full_entry": "le montant"
  },
  {
    "word": "montre",
    "article": "la",
    "pos": "noun",
    "full_entry": "la montre"
  },
  {
    "word": "monumental",
    "article": "",
    "pos": "adj",
    "full_entry": "monumental"
  },
  {
    "word": "moquer",
    "article": "",
    "pos": "verb",
    "full_entry": "moquer"
  },
  {
    "word": "moteur",
    "article": "le",
    "pos": "noun",
    "full_entry": "le moteur"
  },
  {
    "word": "motif",
    "article": "le",
    "pos": "noun",
    "full_entry": "le motif"
  },
  {
    "word": "mouton",
    "article": "le",
    "pos": "noun",
    "full_entry": "le mouton"
  },
  {
    "word": "mural",
    "article": "",
    "pos": "adj",
    "full_entry": "mural"
  },
  {
    "word": "muser",
    "article": "",
    "pos": "verb",
    "full_entry": "muser"
  },
  {
    "word": "musical",
    "article": "",
    "pos": "adj",
    "full_entry": "musical"
  },
  {
    "word": "musulman",
    "article": "",
    "pos": "adj",
    "full_entry": "musulman"
  },
  {
    "word": "mystère",
    "article": "le",
    "pos": "noun",
    "full_entry": "le mystère"
  },
  {
    "word": "mystérieux",
    "article": "",
    "pos": "adj",
    "full_entry": "mystérieux"
  },
  {
    "word": "médecine",
    "article": "la",
    "pos": "noun",
    "full_entry": "la médecine"
  },
  {
    "word": "médias",
    "article": "",
    "pos": "noun",
    "full_entry": "médias"
  },
  {
    "word": "médiéval",
    "article": "",
    "pos": "adj",
    "full_entry": "médiéval"
  },
  {
    "word": "mélanger",
    "article": "",
    "pos": "verb",
    "full_entry": "mélanger"
  },
  {
    "word": "métal",
    "article": "le",
    "pos": "noun",
    "full_entry": "le métal"
  },
  {
    "word": "métropole",
    "article": "la",
    "pos": "noun",
    "full_entry": "la métropole"
  },
  {
    "word": "naissance",
    "article": "la",
    "pos": "noun",
    "full_entry": "la naissance"
  },
  {
    "word": "natation",
    "article": "la",
    "pos": "noun",
    "full_entry": "la natation"
  },
  {
    "word": "naturel",
    "article": "",
    "pos": "adj",
    "full_entry": "naturel"
  },
  {
    "word": "nerveux",
    "article": "",
    "pos": "adj",
    "full_entry": "nerveux"
  },
  {
    "word": "nettoyer",
    "article": "",
    "pos": "verb",
    "full_entry": "nettoyer"
  },
  {
    "word": "neveu",
    "article": "le",
    "pos": "noun",
    "full_entry": "le neveu"
  },
  {
    "word": "niveau",
    "article": "le",
    "pos": "noun",
    "full_entry": "le niveau"
  },
  {
    "word": "nocturne",
    "article": "",
    "pos": "adj",
    "full_entry": "nocturne"
  },
  {
    "word": "notamment",
    "article": "",
    "pos": "adv",
    "full_entry": "notamment"
  },
  {
    "word": "nourriture",
    "article": "la",
    "pos": "noun",
    "full_entry": "la nourriture"
  },
  {
    "word": "nuage",
    "article": "le",
    "pos": "noun",
    "full_entry": "le nuage"
  },
  {
    "word": "numéroter",
    "article": "",
    "pos": "verb",
    "full_entry": "numéroter"
  },
  {
    "word": "nécessaire",
    "article": "",
    "pos": "adj",
    "full_entry": "nécessaire"
  },
  {
    "word": "obliger",
    "article": "",
    "pos": "verb",
    "full_entry": "obliger"
  },
  {
    "word": "occasion",
    "article": "l'",
    "pos": "noun",
    "full_entry": "l' occasion"
  },
  {
    "word": "océan",
    "article": "l'",
    "pos": "noun",
    "full_entry": "l' océan"
  },
  {
    "word": "oignon",
    "article": "l'",
    "pos": "noun",
    "full_entry": "l' oignon"
  },
  {
    "word": "olive",
    "article": "l'",
    "pos": "noun",
    "full_entry": "l' olive"
  },
  {
    "word": "opéra",
    "article": "l'",
    "pos": "noun",
    "full_entry": "l' opéra"
  },
  {
    "word": "or",
    "article": "l'",
    "pos": "noun",
    "full_entry": "l' or"
  },
  {
    "word": "organisme",
    "article": "l'",
    "pos": "noun",
    "full_entry": "l' organisme"
  },
  {
    "word": "oublie",
    "article": "l'",
    "pos": "noun",
    "full_entry": "l' oublie"
  },
  {
    "word": "ouest",
    "article": "l'",
    "pos": "noun",
    "full_entry": "l' ouest"
  },
  {
    "word": "outil",
    "article": "l'",
    "pos": "noun",
    "full_entry": "l' outil"
  },
  {
    "word": "outre-mer",
    "article": "",
    "pos": "adv",
    "full_entry": "outre-mer"
  },
  {
    "word": "pamplemousse",
    "article": "",
    "pos": "noun",
    "full_entry": "pamplemousse"
  },
  {
    "word": "panneau",
    "article": "le",
    "pos": "noun",
    "full_entry": "le panneau"
  },
  {
    "word": "panorama",
    "article": "le",
    "pos": "noun",
    "full_entry": "le panorama"
  },
  {
    "word": "papier",
    "article": "le",
    "pos": "noun",
    "full_entry": "le papier"
  },
  {
    "word": "parapluie",
    "article": "le",
    "pos": "noun",
    "full_entry": "le parapluie"
  },
  {
    "word": "parisien",
    "article": "",
    "pos": "adj",
    "full_entry": "parisien"
  },
  {
    "word": "parole",
    "article": "la",
    "pos": "noun",
    "full_entry": "la parole"
  },
  {
    "word": "particulièrement",
    "article": "",
    "pos": "adv",
    "full_entry": "particulièrement"
  },
  {
    "word": "passionnant",
    "article": "",
    "pos": "adj",
    "full_entry": "passionnant"
  },
  {
    "word": "pat",
    "article": "",
    "pos": "adj",
    "full_entry": "pat"
  },
  {
    "word": "patient",
    "article": "",
    "pos": "adj",
    "full_entry": "patient"
  },
  {
    "word": "patron",
    "article": "le",
    "pos": "noun",
    "full_entry": "le patron"
  },
  {
    "word": "payer",
    "article": "",
    "pos": "verb",
    "full_entry": "payer"
  },
  {
    "word": "peau",
    "article": "la",
    "pos": "noun",
    "full_entry": "la peau"
  },
  {
    "word": "peindre",
    "article": "",
    "pos": "verb",
    "full_entry": "peindre"
  },
  {
    "word": "perdu",
    "article": "",
    "pos": "adj",
    "full_entry": "perdu"
  },
  {
    "word": "perle",
    "article": "la",
    "pos": "noun",
    "full_entry": "la perle"
  },
  {
    "word": "personnel",
    "article": "",
    "pos": "adj",
    "full_entry": "personnel"
  },
  {
    "word": "petit",
    "article": "le",
    "pos": "noun",
    "full_entry": "le petit"
  },
  {
    "word": "petite-fille",
    "article": "la",
    "pos": "noun",
    "full_entry": "la petite-fille"
  },
  {
    "word": "pharmacie",
    "article": "la",
    "pos": "noun",
    "full_entry": "la pharmacie"
  },
  {
    "word": "photocopie",
    "article": "la",
    "pos": "noun",
    "full_entry": "la photocopie"
  },
  {
    "word": "photographe",
    "article": "",
    "pos": "noun",
    "full_entry": "photographe"
  },
  {
    "word": "phrase",
    "article": "la",
    "pos": "noun",
    "full_entry": "la phrase"
  },
  {
    "word": "pis",
    "article": "",
    "pos": "adv",
    "full_entry": "pis"
  },
  {
    "word": "piéton",
    "article": "",
    "pos": "adj",
    "full_entry": "piéton"
  },
  {
    "word": "placer",
    "article": "",
    "pos": "verb",
    "full_entry": "placer"
  },
  {
    "word": "plaisanter",
    "article": "",
    "pos": "verb",
    "full_entry": "plaisanter"
  },
  {
    "word": "planter",
    "article": "",
    "pos": "verb",
    "full_entry": "planter"
  },
  {
    "word": "plastique",
    "article": "",
    "pos": "noun",
    "full_entry": "plastique"
  },
  {
    "word": "plume",
    "article": "la",
    "pos": "noun",
    "full_entry": "la plume"
  },
  {
    "word": "point",
    "article": "le",
    "pos": "noun",
    "full_entry": "le point"
  },
  {
    "word": "polluant",
    "article": "",
    "pos": "adj",
    "full_entry": "polluant"
  },
  {
    "word": "polonais",
    "article": "",
    "pos": "adj",
    "full_entry": "polonais"
  },
  {
    "word": "populaire",
    "article": "",
    "pos": "adj",
    "full_entry": "populaire"
  },
  {
    "word": "porc",
    "article": "le",
    "pos": "noun",
    "full_entry": "le porc"
  },
  {
    "word": "portugais",
    "article": "",
    "pos": "adj",
    "full_entry": "portugais"
  },
  {
    "word": "position",
    "article": "la",
    "pos": "noun",
    "full_entry": "la position"
  },
  {
    "word": "possibilité",
    "article": "la",
    "pos": "noun",
    "full_entry": "la possibilité"
  },
  {
    "word": "poulet",
    "article": "le",
    "pos": "noun",
    "full_entry": "le poulet"
  },
  {
    "word": "poupée",
    "article": "la",
    "pos": "noun",
    "full_entry": "la poupée"
  },
  {
    "word": "pourboire",
    "article": "le",
    "pos": "noun",
    "full_entry": "le pourboire"
  },
  {
    "word": "pousser",
    "article": "",
    "pos": "verb",
    "full_entry": "pousser"
  },
  {
    "word": "poussière",
    "article": "la",
    "pos": "noun",
    "full_entry": "la poussière"
  },
  {
    "word": "poète",
    "article": "",
    "pos": "adj",
    "full_entry": "poète"
  },
  {
    "word": "poésie",
    "article": "la",
    "pos": "noun",
    "full_entry": "la poésie"
  },
  {
    "word": "pratique",
    "article": "",
    "pos": "adj",
    "full_entry": "pratique"
  },
  {
    "word": "pratique",
    "article": "",
    "pos": "noun",
    "full_entry": "pratique"
  },
  {
    "word": "presse",
    "article": "la",
    "pos": "noun",
    "full_entry": "la presse"
  },
  {
    "word": "prisonnier",
    "article": "le",
    "pos": "noun",
    "full_entry": "le prisonnier"
  },
  {
    "word": "privilégier",
    "article": "",
    "pos": "verb",
    "full_entry": "privilégier"
  },
  {
    "word": "proche",
    "article": "",
    "pos": "adj",
    "full_entry": "proche"
  },
  {
    "word": "production",
    "article": "la",
    "pos": "noun",
    "full_entry": "la production"
  },
  {
    "word": "profession",
    "article": "la",
    "pos": "noun",
    "full_entry": "la profession"
  },
  {
    "word": "progrès",
    "article": "le",
    "pos": "noun",
    "full_entry": "le progrès"
  },
  {
    "word": "prouver",
    "article": "",
    "pos": "verb",
    "full_entry": "prouver"
  },
  {
    "word": "proximité",
    "article": "la",
    "pos": "noun",
    "full_entry": "la proximité"
  },
  {
    "word": "pré",
    "article": "le",
    "pos": "noun",
    "full_entry": "le pré"
  },
  {
    "word": "précieux",
    "article": "",
    "pos": "adj",
    "full_entry": "précieux"
  },
  {
    "word": "précis",
    "article": "",
    "pos": "adj",
    "full_entry": "précis"
  },
  {
    "word": "présent",
    "article": "",
    "pos": "adj",
    "full_entry": "présent"
  },
  {
    "word": "présentateur",
    "article": "le",
    "pos": "noun",
    "full_entry": "le présentateur"
  },
  {
    "word": "président",
    "article": "le",
    "pos": "noun",
    "full_entry": "le président"
  },
  {
    "word": "publicité",
    "article": "la",
    "pos": "noun",
    "full_entry": "la publicité"
  },
  {
    "word": "publique",
    "article": "",
    "pos": "adj",
    "full_entry": "publique"
  },
  {
    "word": "pâtisserie",
    "article": "la",
    "pos": "noun",
    "full_entry": "la pâtisserie"
  },
  {
    "word": "période",
    "article": "la",
    "pos": "noun",
    "full_entry": "la période"
  },
  {
    "word": "pétanque",
    "article": "la",
    "pos": "noun",
    "full_entry": "la pétanque"
  },
  {
    "word": "pêche",
    "article": "la",
    "pos": "noun",
    "full_entry": "la pêche"
  },
  {
    "word": "quatre",
    "article": "la",
    "pos": "noun",
    "full_entry": "la quatre"
  },
  {
    "word": "queue",
    "article": "la",
    "pos": "noun",
    "full_entry": "la queue"
  },
  {
    "word": "quotidien",
    "article": "",
    "pos": "adj",
    "full_entry": "quotidien"
  },
  {
    "word": "québécois",
    "article": "",
    "pos": "adj",
    "full_entry": "québécois"
  },
  {
    "word": "rabat",
    "article": "le",
    "pos": "noun",
    "full_entry": "le rabat"
  },
  {
    "word": "radio",
    "article": "",
    "pos": "noun",
    "full_entry": "radio"
  },
  {
    "word": "radio",
    "article": "",
    "pos": "adj",
    "full_entry": "radio"
  },
  {
    "word": "raide",
    "article": "",
    "pos": "adj",
    "full_entry": "raide"
  },
  {
    "word": "ramasser",
    "article": "",
    "pos": "verb",
    "full_entry": "ramasser"
  },
  {
    "word": "ramener",
    "article": "",
    "pos": "verb",
    "full_entry": "ramener"
  },
  {
    "word": "randonnée",
    "article": "la",
    "pos": "noun",
    "full_entry": "la randonnée"
  },
  {
    "word": "rapprocher",
    "article": "",
    "pos": "verb",
    "full_entry": "rapprocher"
  },
  {
    "word": "rare",
    "article": "",
    "pos": "adj",
    "full_entry": "rare"
  },
  {
    "word": "rassurer",
    "article": "",
    "pos": "verb",
    "full_entry": "rassurer"
  },
  {
    "word": "rattraper",
    "article": "",
    "pos": "verb",
    "full_entry": "rattraper"
  },
  {
    "word": "recomposer",
    "article": "",
    "pos": "verb",
    "full_entry": "recomposer"
  },
  {
    "word": "recouvrir",
    "article": "",
    "pos": "verb",
    "full_entry": "recouvrir"
  },
  {
    "word": "relation",
    "article": "la",
    "pos": "noun",
    "full_entry": "la relation"
  },
  {
    "word": "religion",
    "article": "la",
    "pos": "noun",
    "full_entry": "la religion"
  },
  {
    "word": "remplir",
    "article": "",
    "pos": "verb",
    "full_entry": "remplir"
  },
  {
    "word": "remporter",
    "article": "",
    "pos": "verb",
    "full_entry": "remporter"
  },
  {
    "word": "renaissance",
    "article": "la",
    "pos": "noun",
    "full_entry": "la renaissance"
  },
  {
    "word": "renseigner",
    "article": "",
    "pos": "verb",
    "full_entry": "renseigner"
  },
  {
    "word": "responsabilité",
    "article": "la",
    "pos": "noun",
    "full_entry": "la responsabilité"
  },
  {
    "word": "restau",
    "article": "le",
    "pos": "noun",
    "full_entry": "le restau"
  },
  {
    "word": "restaurer",
    "article": "",
    "pos": "verb",
    "full_entry": "restaurer"
  },
  {
    "word": "resto",
    "article": "le",
    "pos": "noun",
    "full_entry": "le resto"
  },
  {
    "word": "retenir",
    "article": "",
    "pos": "verb",
    "full_entry": "retenir"
  },
  {
    "word": "retraite",
    "article": "la",
    "pos": "noun",
    "full_entry": "la retraite"
  },
  {
    "word": "rhum",
    "article": "le",
    "pos": "noun",
    "full_entry": "le rhum"
  },
  {
    "word": "richesse",
    "article": "la",
    "pos": "noun",
    "full_entry": "la richesse"
  },
  {
    "word": "rire",
    "article": "le",
    "pos": "noun",
    "full_entry": "le rire"
  },
  {
    "word": "rive",
    "article": "la",
    "pos": "noun",
    "full_entry": "la rive"
  },
  {
    "word": "robe",
    "article": "la",
    "pos": "noun",
    "full_entry": "la robe"
  },
  {
    "word": "romain",
    "article": "",
    "pos": "adj",
    "full_entry": "romain"
  },
  {
    "word": "rond",
    "article": "",
    "pos": "adj",
    "full_entry": "rond"
  },
  {
    "word": "rosier",
    "article": "le",
    "pos": "noun",
    "full_entry": "le rosier"
  },
  {
    "word": "royal",
    "article": "",
    "pos": "adj",
    "full_entry": "royal"
  },
  {
    "word": "royaume",
    "article": "le",
    "pos": "noun",
    "full_entry": "le royaume"
  },
  {
    "word": "russe",
    "article": "",
    "pos": "adj",
    "full_entry": "russe"
  },
  {
    "word": "ré",
    "article": "le",
    "pos": "noun",
    "full_entry": "le ré"
  },
  {
    "word": "réalisateur",
    "article": "le",
    "pos": "noun",
    "full_entry": "le réalisateur"
  },
  {
    "word": "réception",
    "article": "la",
    "pos": "noun",
    "full_entry": "la réception"
  },
  {
    "word": "rédiger",
    "article": "",
    "pos": "verb",
    "full_entry": "rédiger"
  },
  {
    "word": "répondeur",
    "article": "le",
    "pos": "noun",
    "full_entry": "le répondeur"
  },
  {
    "word": "réserve",
    "article": "la",
    "pos": "noun",
    "full_entry": "la réserve"
  },
  {
    "word": "résidence",
    "article": "la",
    "pos": "noun",
    "full_entry": "la résidence"
  },
  {
    "word": "résistant",
    "article": "le",
    "pos": "noun",
    "full_entry": "le résistant"
  },
  {
    "word": "sable",
    "article": "le",
    "pos": "noun",
    "full_entry": "le sable"
  },
  {
    "word": "sage",
    "article": "",
    "pos": "adj",
    "full_entry": "sage"
  },
  {
    "word": "saison",
    "article": "la",
    "pos": "noun",
    "full_entry": "la saison"
  },
  {
    "word": "salutation",
    "article": "la",
    "pos": "noun",
    "full_entry": "la salutation"
  },
  {
    "word": "sang",
    "article": "le",
    "pos": "noun",
    "full_entry": "le sang"
  },
  {
    "word": "sardine",
    "article": "la",
    "pos": "noun",
    "full_entry": "la sardine"
  },
  {
    "word": "saucisson",
    "article": "le",
    "pos": "noun",
    "full_entry": "le saucisson"
  },
  {
    "word": "saumon",
    "article": "le",
    "pos": "noun",
    "full_entry": "le saumon"
  },
  {
    "word": "sauter",
    "article": "",
    "pos": "verb",
    "full_entry": "sauter"
  },
  {
    "word": "sauvage",
    "article": "",
    "pos": "adj",
    "full_entry": "sauvage"
  },
  {
    "word": "sculpture",
    "article": "la",
    "pos": "noun",
    "full_entry": "la sculpture"
  },
  {
    "word": "scène",
    "article": "la",
    "pos": "noun",
    "full_entry": "la scène"
  },
  {
    "word": "secrétariat",
    "article": "le",
    "pos": "noun",
    "full_entry": "le secrétariat"
  },
  {
    "word": "secteur",
    "article": "le",
    "pos": "noun",
    "full_entry": "le secteur"
  },
  {
    "word": "sensible",
    "article": "",
    "pos": "adj",
    "full_entry": "sensible"
  },
  {
    "word": "sentiment",
    "article": "le",
    "pos": "noun",
    "full_entry": "le sentiment"
  },
  {
    "word": "seul",
    "article": "le",
    "pos": "noun",
    "full_entry": "le seul"
  },
  {
    "word": "signe",
    "article": "le",
    "pos": "noun",
    "full_entry": "le signe"
  },
  {
    "word": "simplement",
    "article": "",
    "pos": "adv",
    "full_entry": "simplement"
  },
  {
    "word": "sincère",
    "article": "",
    "pos": "adj",
    "full_entry": "sincère"
  },
  {
    "word": "sirop",
    "article": "le",
    "pos": "noun",
    "full_entry": "le sirop"
  },
  {
    "word": "skier",
    "article": "",
    "pos": "verb",
    "full_entry": "skier"
  },
  {
    "word": "social",
    "article": "",
    "pos": "adj",
    "full_entry": "social"
  },
  {
    "word": "soif",
    "article": "la",
    "pos": "noun",
    "full_entry": "la soif"
  },
  {
    "word": "solaire",
    "article": "",
    "pos": "adj",
    "full_entry": "solaire"
  },
  {
    "word": "soldat",
    "article": "le",
    "pos": "noun",
    "full_entry": "le soldat"
  },
  {
    "word": "solidarité",
    "article": "la",
    "pos": "noun",
    "full_entry": "la solidarité"
  },
  {
    "word": "sommeil",
    "article": "le",
    "pos": "noun",
    "full_entry": "le sommeil"
  },
  {
    "word": "soulier",
    "article": "le",
    "pos": "noun",
    "full_entry": "le soulier"
  },
  {
    "word": "souriant",
    "article": "",
    "pos": "adj",
    "full_entry": "souriant"
  },
  {
    "word": "spaghetti",
    "article": "le",
    "pos": "noun",
    "full_entry": "le spaghetti"
  },
  {
    "word": "spectaculaire",
    "article": "",
    "pos": "adj",
    "full_entry": "spectaculaire"
  },
  {
    "word": "spectateur",
    "article": "le",
    "pos": "noun",
    "full_entry": "le spectateur"
  },
  {
    "word": "spécialement",
    "article": "",
    "pos": "adv",
    "full_entry": "spécialement"
  },
  {
    "word": "stage",
    "article": "le",
    "pos": "noun",
    "full_entry": "le stage"
  },
  {
    "word": "stupide",
    "article": "",
    "pos": "adj",
    "full_entry": "stupide"
  },
  {
    "word": "style",
    "article": "le",
    "pos": "noun",
    "full_entry": "le style"
  },
  {
    "word": "sud-est",
    "article": "le",
    "pos": "noun",
    "full_entry": "le sud-est"
  },
  {
    "word": "sud-ouest",
    "article": "le",
    "pos": "noun",
    "full_entry": "le sud-ouest"
  },
  {
    "word": "suffire",
    "article": "",
    "pos": "verb",
    "full_entry": "suffire"
  },
  {
    "word": "suivant",
    "article": "",
    "pos": "adj",
    "full_entry": "suivant"
  },
  {
    "word": "sujet",
    "article": "le",
    "pos": "noun",
    "full_entry": "le sujet"
  },
  {
    "word": "surveiller",
    "article": "",
    "pos": "verb",
    "full_entry": "surveiller"
  },
  {
    "word": "symbole",
    "article": "le",
    "pos": "noun",
    "full_entry": "le symbole"
  },
  {
    "word": "symboliser",
    "article": "",
    "pos": "verb",
    "full_entry": "symboliser"
  },
  {
    "word": "sympathie",
    "article": "la",
    "pos": "noun",
    "full_entry": "la sympathie"
  },
  {
    "word": "sécurité",
    "article": "la",
    "pos": "noun",
    "full_entry": "la sécurité"
  },
  {
    "word": "séparer",
    "article": "",
    "pos": "verb",
    "full_entry": "séparer"
  },
  {
    "word": "sévère",
    "article": "",
    "pos": "adj",
    "full_entry": "sévère"
  },
  {
    "word": "taire",
    "article": "",
    "pos": "verb",
    "full_entry": "taire"
  },
  {
    "word": "tapisserie",
    "article": "la",
    "pos": "noun",
    "full_entry": "la tapisserie"
  },
  {
    "word": "tarte",
    "article": "la",
    "pos": "noun",
    "full_entry": "la tarte"
  },
  {
    "word": "terrain",
    "article": "le",
    "pos": "noun",
    "full_entry": "le terrain"
  },
  {
    "word": "terrifiant",
    "article": "",
    "pos": "adj",
    "full_entry": "terrifiant"
  },
  {
    "word": "territoire",
    "article": "le",
    "pos": "noun",
    "full_entry": "le territoire"
  },
  {
    "word": "titre",
    "article": "le",
    "pos": "noun",
    "full_entry": "le titre"
  },
  {
    "word": "total",
    "article": "le",
    "pos": "noun",
    "full_entry": "le total"
  },
  {
    "word": "touristique",
    "article": "",
    "pos": "adj",
    "full_entry": "touristique"
  },
  {
    "word": "traditionnel",
    "article": "",
    "pos": "adj",
    "full_entry": "traditionnel"
  },
  {
    "word": "traditionnellement",
    "article": "",
    "pos": "adv",
    "full_entry": "traditionnellement"
  },
  {
    "word": "tranquillement",
    "article": "",
    "pos": "adv",
    "full_entry": "tranquillement"
  },
  {
    "word": "transport",
    "article": "le",
    "pos": "noun",
    "full_entry": "le transport"
  },
  {
    "word": "traversée",
    "article": "la",
    "pos": "noun",
    "full_entry": "la traversée"
  },
  {
    "word": "trop",
    "article": "",
    "pos": "noun",
    "full_entry": "trop"
  },
  {
    "word": "tuer",
    "article": "",
    "pos": "verb",
    "full_entry": "tuer"
  },
  {
    "word": "téléviser",
    "article": "",
    "pos": "verb",
    "full_entry": "téléviser"
  },
  {
    "word": "union",
    "article": "l'",
    "pos": "noun",
    "full_entry": "l' union"
  },
  {
    "word": "universitaire",
    "article": "",
    "pos": "adj",
    "full_entry": "universitaire"
  },
  {
    "word": "utile",
    "article": "",
    "pos": "adj",
    "full_entry": "utile"
  },
  {
    "word": "vain",
    "article": "",
    "pos": "adj",
    "full_entry": "vain"
  },
  {
    "word": "valeur",
    "article": "la",
    "pos": "noun",
    "full_entry": "la valeur"
  },
  {
    "word": "vendeur",
    "article": "le",
    "pos": "noun",
    "full_entry": "le vendeur"
  },
  {
    "word": "version",
    "article": "la",
    "pos": "noun",
    "full_entry": "la version"
  },
  {
    "word": "veste",
    "article": "la",
    "pos": "noun",
    "full_entry": "la veste"
  },
  {
    "word": "vestige",
    "article": "le",
    "pos": "noun",
    "full_entry": "le vestige"
  },
  {
    "word": "vexer",
    "article": "",
    "pos": "verb",
    "full_entry": "vexer"
  },
  {
    "word": "vif",
    "article": "",
    "pos": "adj",
    "full_entry": "vif"
  },
  {
    "word": "violent",
    "article": "",
    "pos": "adj",
    "full_entry": "violent"
  },
  {
    "word": "visiteur",
    "article": "le",
    "pos": "noun",
    "full_entry": "le visiteur"
  },
  {
    "word": "voeu",
    "article": "le",
    "pos": "noun",
    "full_entry": "le voeu"
  },
  {
    "word": "voleur",
    "article": "le",
    "pos": "noun",
    "full_entry": "le voleur"
  },
  {
    "word": "voyageur",
    "article": "le",
    "pos": "noun",
    "full_entry": "le voyageur"
  },
  {
    "word": "véhicule",
    "article": "le",
    "pos": "noun",
    "full_entry": "le véhicule"
  },
  {
    "word": "vérifier",
    "article": "",
    "pos": "verb",
    "full_entry": "vérifier"
  },
  {
    "word": "yaourt",
    "article": "le",
    "pos": "noun",
    "full_entry": "le yaourt"
  },
  {
    "word": "zoo",
    "article": "le",
    "pos": "noun",
    "full_entry": "le zoo"
  },
  {
    "word": "échange",
    "article": "l'",
    "pos": "noun",
    "full_entry": "l' échange"
  },
  {
    "word": "écharpe",
    "article": "l'",
    "pos": "noun",
    "full_entry": "l' écharpe"
  },
  {
    "word": "éclairage",
    "article": "l'",
    "pos": "noun",
    "full_entry": "l' éclairage"
  },
  {
    "word": "économie",
    "article": "l'",
    "pos": "noun",
    "full_entry": "l' économie"
  },
  {
    "word": "économique",
    "article": "",
    "pos": "adj",
    "full_entry": "économique"
  },
  {
    "word": "écu",
    "article": "l'",
    "pos": "noun",
    "full_entry": "l' écu"
  },
  {
    "word": "écurie",
    "article": "l'",
    "pos": "noun",
    "full_entry": "l' écurie"
  },
  {
    "word": "électrique",
    "article": "",
    "pos": "adj",
    "full_entry": "électrique"
  },
  {
    "word": "élire",
    "article": "",
    "pos": "verb",
    "full_entry": "élire"
  },
  {
    "word": "élégant",
    "article": "",
    "pos": "adj",
    "full_entry": "élégant"
  },
  {
    "word": "élément",
    "article": "l'",
    "pos": "noun",
    "full_entry": "l' élément"
  },
  {
    "word": "émission",
    "article": "l'",
    "pos": "noun",
    "full_entry": "l' émission"
  },
  {
    "word": "énergie",
    "article": "l'",
    "pos": "noun",
    "full_entry": "l' énergie"
  },
  {
    "word": "épeler",
    "article": "",
    "pos": "verb",
    "full_entry": "épeler"
  },
  {
    "word": "épice",
    "article": "l'",
    "pos": "noun",
    "full_entry": "l' épice"
  },
  {
    "word": "épicer",
    "article": "",
    "pos": "verb",
    "full_entry": "épicer"
  },
  {
    "word": "épisode",
    "article": "l'",
    "pos": "noun",
    "full_entry": "l' épisode"
  },
  {
    "word": "éplucher",
    "article": "",
    "pos": "verb",
    "full_entry": "éplucher"
  },
  {
    "word": "épée",
    "article": "l'",
    "pos": "noun",
    "full_entry": "l' épée"
  },
  {
    "word": "équipe",
    "article": "l'",
    "pos": "noun",
    "full_entry": "l' équipe"
  },
  {
    "word": "équipement",
    "article": "l'",
    "pos": "noun",
    "full_entry": "l' équipement"
  },
  {
    "word": "étonner",
    "article": "",
    "pos": "verb",
    "full_entry": "étonner"
  },
  {
    "word": "étroit",
    "article": "",
    "pos": "adj",
    "full_entry": "étroit"
  },
  {
    "word": "évoluer",
    "article": "",
    "pos": "verb",
    "full_entry": "évoluer"
  },
  {
    "word": "évolution",
    "article": "l'",
    "pos": "noun",
    "full_entry": "l' évolution"
  },
  {
    "word": "évoquer",
    "article": "",
    "pos": "verb",
    "full_entry": "évoquer"
  }
]